{
  "accentColor": "{{appsmith.theme.colors.primaryColor}}",
  "animateLoading": true,
  "borderRadius": "{{appsmith.theme.borderRadius.appBorderRadius}}",
  "bottomRow": 8,
  "boxShadow": "none",
  "capSide": 0,
  "capType": "nc",
  "displayName": "Divider",
  "dividerColor": "#5E6C9E",
  "dynamicBindingPathList": [],
  "dynamicTriggerPathList": [],
  "hideCard": false,
  "iconSVG": "/static/media/icon.cbe8f608ca868e1eb44607e5fbd4a9e5.svg",
  "isDeprecated": false,
  "isLoading": false,
  "isVisible": true,
  "key": "c3xzqeinqm",
  "leftColumn": 2,
  "orientation": "horizontal",
  "originalBottomRow": 13,
  "originalTopRow": 9,
  "parentColumnSpace": 3.7119140625,
  "parentId": "rb1lm2c6sb",
  "parentRowSpace": 10,
  "renderMode": "CANVAS",
  "rightColumn": 63,
  "searchTags": [
    "line"
  ],
  "strokeStyle": "solid",
  "thickness": 2,
  "topRow": 4,
  "type": "DIVIDER_WIDGET",
  "version": 1,
  "widgetId": "rf388lxqda",
  "widgetName": "Divider1"
}